LICENSE.txt
MANIFEST.in
README.md
setup.py
dotcs_community/__init__.py
dotcs_community/robot.py
dotcs_community.egg-info/PKG-INFO
dotcs_community.egg-info/SOURCES.txt
dotcs_community.egg-info/dependency_links.txt
dotcs_community.egg-info/requires.txt
dotcs_community.egg-info/top_level.txt
dotcs_community/PyPI/SpaceRectangularCoordinateSystem.py
dotcs_community/PyPI/TDES.py
dotcs_community/PyPI/__init__.py
dotcs_community/dotcs_ex/__init__.py
dotcs_community/dotcs_ex/_error.py
dotcs_community/dotcs_ex/_plugin.py
dotcs_community/dotcs_ex/color.py
dotcs_community/dotcs_ex/color_input.py
dotcs_community/dotcs_ex/const.py
dotcs_community/dotcs_ex/date.py
dotcs_community/dotcs_ex/error.py
dotcs_community/dotcs_ex/mc_color.py
dotcs_community/dotcs_ex/plugin.py
dotcs_community/dotcs_ex/system.py
dotcs_community/dotcs_ex/tool.py
dotcs_community/dotcs_ex/warning.py
dotcs_community/dotcs_ex/welcome.py
dotcs_community/dotcs_ex/config/__init__.py
dotcs_community/dotcs_ex/config/debug.py
dotcs_community/dotcs_ex/config/fb_set.py
dotcs_community/dotcs_ex/config/init.py
dotcs_community/dotcs_ex/config/update_server.py
dotcs_community/dotcs_ex/game/__init__.py
dotcs_community/dotcs_ex/game/log.py
dotcs_community/dotcs_ex/game/threading.py
dotcs_community/proxy/__init__.py
dotcs_community/proxy/conn.py
dotcs_community/proxy/fbconn.dll
dotcs_community/proxy/fbconn_Linux_aarch64.dylib
dotcs_community/proxy/fbconn_Windows.dylib
dotcs_community/proxy/libfbconn.so