Metadata-Version: 2.1
Name: dotcs-community
Version: 0.11.0
Summary: DotCS 社区版 : 基于 fastbuilder 的 插件管理工具
Home-page: https://github.com/xX7912Xx/dotcs
Author: xX7912Xx,去幻想乡的老art
Author-email: 121980156@qq.com
Classifier: Programming Language :: Python :: 3
Classifier: Operating System :: OS Independent
Requires-Python: >=3.10
License-File: LICENSE.txt
